ed_explorer_stats/__init__.py
ed_explorer_stats/colors.py
ed_explorer_stats/exploration_stats.py
ed_explorer_stats/read_journals.py
ed_explorer_stats/stellar_info.py
ed_explorer_stats/time_formatting.py
ed_explorer_stats/stat_groups/__init__.py
ed_explorer_stats/stat_groups/biological.py
ed_explorer_stats/stat_groups/collector.py
ed_explorer_stats/stat_groups/fuel_scooped.py
ed_explorer_stats/stat_groups/gravity.py
ed_explorer_stats/stat_groups/min_max_collector.py
ed_explorer_stats/stat_groups/most_bodies.py
ed_explorer_stats/stat_groups/orbital_period.py
ed_explorer_stats/stat_groups/radius.py
ed_explorer_stats/stat_groups/rotation_period.py
ed_explorer_stats/stat_groups/scanned_bodies.py
ed_explorer_stats/stat_groups/surface_scans.py
ed_explorer_stats/stat_groups/visited_systems.py
ed_explorer_stats-1.0.2.dist-info/METADATA
ed_explorer_stats-1.0.2.dist-info/WHEEL
ed_explorer_stats-1.0.2.dist-info/entry_points.txt
ed_explorer_stats-1.0.2.dist-info/top_level.txt
ed_explorer_stats-1.0.2.dist-info/RECORD
