Metadata-Version: 2.1
Name: ed-explorer-stats
Version: 1.0.2
Summary: Display interesting stats for Elite Dangerous explorers
Project-URL: Homepage, https://github.com/Treescrub/ED-Explorer-Stats
Project-URL: Repository, https://github.com/Treescrub/ED-Explorer-Stats.git
Classifier: Development Status :: 4 - Beta
Classifier: Environment :: Console
Classifier: Intended Audience :: End Users/Desktop
Classifier: License :: OSI Approved :: MIT License
Classifier: Natural Language :: English
Classifier: Programming Language :: Python :: 3
Classifier: Programming Language :: Python :: 3.10
Classifier: Topic :: Games/Entertainment
Requires-Dist: colorama
